OneXAPI/__init__.py
OneXAPI/Binance/__init__.py
OneXAPI/Upbit/__init__.py
OneXAPI/Upbit/Indonesia/__init__.py
OneXAPI/Upbit/Singapore/__init__.py
OneXAPI/Upbit/Thailand/__init__.py
OneXAPI/internal/__init__.py
OneXAPI/internal/util.py
OneXAPI/internal/instruments/__init__.py
OneXAPI/internal/instruments/futures.py
OneXAPI/internal/instruments/spot.py
OneXAPI-0.1.0.dist-info/LICENSE.md
OneXAPI-0.1.0.dist-info/METADATA
OneXAPI-0.1.0.dist-info/WHEEL
OneXAPI-0.1.0.dist-info/top_level.txt
OneXAPI-0.1.0.dist-info/RECORD
