Metadata-Version: 2.1
Name: OneXAPI
Version: 0.1.0
Summary: For Beta Test
Home-page: https://github.com/OneXAPI/OneXAPI_Python
Author: Libera Inc.
Author-email: ceo@libera.or.kr
License: Attribution-NonCommercial-ShareAlike 4.0 International (CC BY-NC-SA 4.0)
Project-URL: Homepage, https://github.com/OneXAPI/OneXAPI_Python
Project-URL: Documentation, https://onexapi.github.io/OneXAPI-Reference/
Platform: UNKNOWN
Requires-Python: >=3.6
License-File: LICENSE.md
Requires-Dist: tqdm (==4.64.1)
